dicttoxml2/__init__.py
dicttoxml2/api.py
dicttoxml2/converters.py
dicttoxml2/utils.py
dicttoxml2/version.py
dicttoxml2-2.0.0.dist-info/LICENCE.txt
dicttoxml2-2.0.0.dist-info/METADATA
dicttoxml2-2.0.0.dist-info/WHEEL
dicttoxml2-2.0.0.dist-info/top_level.txt
dicttoxml2-2.0.0.dist-info/RECORD
