Metadata-Version: 2.1
Name: dicttoxml2
Version: 2.0.0
Summary: Converts a Python dictionary or other native data type into a valid XML string. 
Home-page: https://github.com/quandyfactory/dicttoxml
Author: Ryan McGreal
Author-email: ryan@quandyfactory.com
License: GPL-2.0
Platform: UNKNOWN
Classifier: License :: OSI Approved :: GNU General Public License v2 (GPLv2)
Classifier: Development Status :: 5 - Production/Stable
Classifier: Intended Audience :: Developers
Classifier: Operating System :: OS Independent
Classifier: Programming Language :: Python
Classifier: Programming Language :: Python :: 3
Classifier: Programming Language :: Python :: 3.7
Classifier: Programming Language :: Python :: 3.8
Classifier: Programming Language :: Python :: 3.9
Classifier: Programming Language :: Python :: 3.10
Classifier: Programming Language :: Python :: 3.11
Requires-Python: >=3.7, <4
License-File: LICENCE.txt
